<?xml version="1.0" encoding="UTF-8"?><ImplementationGuide xmlns="http://hl7.org/fhir"><id value="davinci-hrex"/><meta><versionId value="3"/><lastUpdated value="2019-01-28T10:38:08.469-05:00"/></meta><url value="http://hl7.org/fhir/us/davinci-hrex"/><version value="0.0.1"/><name value="Da Vinci eHealth Record Exchange"/><status value="draft"/><description value="This Use Case provides guidance to implementers regarding exchange of a patients eHealth Records. The Use Case is very broad encompassing the following scenarios: &#xA;&#xA;* Exchange of quality measure data to support HEDIS/Stars quality measures,&#xA;* Exchange of clinical information generated by providers during the course of care, and &#xA;* Exchange of clinical information gathered during the claims process by payers. &#xA;&#xA;The exchange of quality measure data can be from Provider to Payer, or Payer to Provider. The exchange of clinical information can be from Provider to Provider, Provider to Payer or Payer to Provider. This Use Case defines a broad set of profiles and interactions that may be utilized to accomplish this wide range of **eHealth Record exchange**. It also includes narrower implementation guidance that demonstrates how to use elements of the framework to accomplish each specific type of information exchange.&#xA;"/><fhirVersion value="4.0.0"/></ImplementationGuide>